hash_sentences/__init__.py
hash_sentences/__main__.py
hash_sentences/contractions.py
hash_sentences/divide_conquer_optimize_split.py
hash_sentences/embed_path_tuples.py
hash_sentences/expanding_contractions.py
hash_sentences/hash_function_representations_info_theoretic_optimization.py
hash_sentences/hash_sentences.py
hash_sentences/information_theoretic_measures_hashcodes.py
hash_sentences/nonascii_text_processing.py
hash_sentences/parallel_computing.py
hash_sentences/parallel_computing_wrapper.py
hash_sentences/random_k_nearest_neighbors_hash.py
hash_sentences/random_maximum_margin_hash.py
hash_sentences/random_neural_hash.py
hash_sentences/rnn_hash_model.py
hash_sentences/script_hash_sentences.py
hash_sentences/text_kernel.py
hash_sentences/total_correlations_estimation.py
hash_sentences/word_embeddings.py
hfr-1.0.0.dist-info/METADATA
hfr-1.0.0.dist-info/WHEEL
hfr-1.0.0.dist-info/entry_points.txt
hfr-1.0.0.dist-info/top_level.txt
hfr-1.0.0.dist-info/RECORD
