Metadata-Version: 2.1
Name: hfr
Version: 1.0.0
Summary: Hash function representations
Home-page: https://github.com/sgarg87/HFR
Author: Sahil Garg
Author-email: sahil.garg.cs@gmail.com
License: MIT
Platform: UNKNOWN
Classifier: License :: OSI Approved :: MIT License
Classifier: Programming Language :: Python :: 3
Classifier: Programming Language :: Python :: 3.7
Requires-Dist: numpy
Requires-Dist: nltk
Requires-Dist: keras
Requires-Dist: Cython
Requires-Dist: scipy
Requires-Dist: scikit-learn
